{
 "cells": [
  {
   "cell_type": "code",
   "execution_count": 1,
   "metadata": {},
   "outputs": [],
   "source": [
    "import tool"
   ]
  },
  {
   "cell_type": "code",
   "execution_count": 2,
   "metadata": {},
   "outputs": [
    {
     "name": "stdout",
     "output_type": "stream",
     "text": [
      "Hello World!\n"
     ]
    }
   ],
   "source": [
    "import test00"
   ]
  },
  {
   "cell_type": "code",
   "execution_count": 3,
   "metadata": {},
   "outputs": [
    {
     "name": "stdout",
     "output_type": "stream",
     "text": [
      "  1           0 LOAD_NAME                0 (print)\n",
      "              2 LOAD_CONST               0 ('Hello World!')\n",
      "              4 CALL_FUNCTION            1\n",
      "              6 POP_TOP\n",
      "              8 LOAD_CONST               1 (None)\n",
      "             10 RETURN_VALUE\n",
      "\n"
     ]
    }
   ],
   "source": [
    "tool.run('python -m dis test00.py')"
   ]
  },
  {
   "cell_type": "code",
   "execution_count": 4,
   "metadata": {},
   "outputs": [
    {
     "name": "stdout",
     "output_type": "stream",
     "text": [
      "a\n"
     ]
    }
   ],
   "source": [
    "import test01\n",
    "test01.func('a')"
   ]
  },
  {
   "cell_type": "code",
   "execution_count": 5,
   "metadata": {},
   "outputs": [
    {
     "data": {
      "text/plain": [
       "b'd\\x00d\\x01\\x84\\x00Z\\x00d\\x02S\\x00'"
      ]
     },
     "execution_count": 5,
     "metadata": {},
     "output_type": "execute_result"
    }
   ],
   "source": [
    "c = compile(open('test01.py').read(), 'test01.py', 'exec')\n",
    "c.co_code"
   ]
  },
  {
   "cell_type": "code",
   "execution_count": 6,
   "metadata": {},
   "outputs": [
    {
     "data": {
      "text/plain": [
       "[100, 0, 100, 1, 132, 0, 90, 0, 100, 2, 83, 0]"
      ]
     },
     "execution_count": 6,
     "metadata": {},
     "output_type": "execute_result"
    }
   ],
   "source": [
    "[byte for byte in c.co_code]"
   ]
  },
  {
   "cell_type": "code",
   "execution_count": 7,
   "metadata": {},
   "outputs": [
    {
     "name": "stdout",
     "output_type": "stream",
     "text": [
      "  1           0 LOAD_CONST               0 (<code object func at 0x7f844ac30030, file \"test01.py\", line 1>)\n",
      "              2 LOAD_CONST               1 ('func')\n",
      "              4 MAKE_FUNCTION            0\n",
      "              6 STORE_NAME               0 (func)\n",
      "              8 LOAD_CONST               2 (None)\n",
      "             10 RETURN_VALUE\n",
      "\n",
      "Disassembly of <code object func at 0x7f844ac30030, file \"test01.py\", line 1>:\n",
      "  2           0 LOAD_GLOBAL              0 (print)\n",
      "              2 LOAD_FAST                0 (a)\n",
      "              4 CALL_FUNCTION            1\n",
      "              6 POP_TOP\n",
      "              8 LOAD_CONST               0 (None)\n",
      "             10 RETURN_VALUE\n",
      "\n"
     ]
    }
   ],
   "source": [
    "tool.run('python -m dis test01.py')"
   ]
  }
 ],
 "metadata": {
  "kernelspec": {
   "display_name": "Python 3",
   "language": "python",
   "name": "python3"
  },
  "language_info": {
   "codemirror_mode": {
    "name": "ipython",
    "version": 3
   },
   "file_extension": ".py",
   "mimetype": "text/x-python",
   "name": "python",
   "nbconvert_exporter": "python",
   "pygments_lexer": "ipython3",
   "version": "3.7.3"
  }
 },
 "nbformat": 4,
 "nbformat_minor": 2
}
